GroupMultiNeSS/MASE.py
GroupMultiNeSS/__init__.py
GroupMultiNeSS/base.py
GroupMultiNeSS/data_generation.py
GroupMultiNeSS/group_multiness.py
GroupMultiNeSS/multiness.py
GroupMultiNeSS/shared_space_hunting.py
GroupMultiNeSS/utils.py
groupmultiness-0.0.3.dist-info/licenses/LICENSE
groupmultiness-0.0.3.dist-info/METADATA
groupmultiness-0.0.3.dist-info/WHEEL
groupmultiness-0.0.3.dist-info/top_level.txt
groupmultiness-0.0.3.dist-info/RECORD
