Metadata-Version: 2.4
Name: GroupMultiNeSS
Version: 0.0.3
Summary: GroupMultiNeSS package
Author: Alexander Kagan
Author-email: <amkagan@umich.edu>
Keywords: python,multiplex networks,multiness,latent space models
Classifier: Development Status :: 3 - Alpha
Classifier: Intended Audience :: Education
Classifier: Programming Language :: Python :: 2
Classifier: Programming Language :: Python :: 3
Classifier: Operating System :: MacOS :: MacOS X
Classifier: Operating System :: Microsoft :: Windows
License-File: LICENSE
Requires-Dist: numpy<2
Requires-Dist: scipy
Requires-Dist: typing
Requires-Dist: joblib
Requires-Dist: matplotlib
Requires-Dist: seaborn
Requires-Dist: statsmodels
Requires-Dist: scikit-learn
Requires-Dist: more_itertools
Dynamic: author
Dynamic: author-email
Dynamic: classifier
Dynamic: description
Dynamic: description-content-type
Dynamic: keywords
Dynamic: license-file
Dynamic: requires-dist
Dynamic: summary
